onya/__about__.py
onya/__init__.py
onya/graph.py
onya/terms.py
onya/util.py
onya/cli/__init__.py
onya/cli/onya.py
onya/contrib/mkdcomments.py
onya/serial/__init__.py
onya/serial/graphviz.py
onya/serial/literate.py
onya/serial/literate_lex.py
onya/serial/litparse_util.py
onya/serial/mermaid.py
onya-0.2.0.dist-info/METADATA
onya-0.2.0.dist-info/WHEEL
onya-0.2.0.dist-info/entry_points.txt
onya-0.2.0.dist-info/licenses/LICENSE
onya-0.2.0.dist-info/licenses/LICENSE-spec
onya-0.2.0.dist-info/RECORD
