Metadata-Version: 2.4
Name: Onya
Version: 0.2.0
Summary: Knowledge graph (property graph-style) model and serialization for web resources
Project-URL: Homepage, https://github.com/OoriData/Onya
Project-URL: Repository, https://github.com/OoriData/Onya
Project-URL: Issues, https://github.com/OoriData/Onya/issues
Author-email: Uche Ogbuji <uche@ogbuji.net>
License: Apache-2.0
License-File: LICENSE
License-File: LICENSE-spec
Keywords: data,graph,linked-data,rdf,web
Classifier: Development Status :: 4 - Beta
Classifier: License :: OSI Approved :: Apache Software License
Classifier: Operating System :: OS Independent
Classifier: Programming Language :: Python
Classifier: Programming Language :: Python :: 3.12
Classifier: Programming Language :: Python :: 3.13
Classifier: Programming Language :: Python :: Implementation :: CPython
Classifier: Programming Language :: Python :: Implementation :: PyPy
Classifier: Topic :: Software Development :: Libraries
Classifier: Topic :: Utilities
Requires-Python: >=3.12
Requires-Dist: amara>=4.0.1
Requires-Dist: fire
Requires-Dist: markdown
Requires-Dist: pyparsing
Provides-Extra: demo
Provides-Extra: dev
Requires-Dist: build; extra == 'dev'
Requires-Dist: hatch; extra == 'dev'
Requires-Dist: pipdeptree; extra == 'dev'
Requires-Dist: pytest; extra == 'dev'
Requires-Dist: pytest-asyncio; extra == 'dev'
Requires-Dist: pytest-mock; extra == 'dev'
Requires-Dist: ruff; extra == 'dev'
Requires-Dist: twine; extra == 'dev'
